takeover/__self__.py
takeover/takeover.py
takeover.py-1.0.0.dist-info/LICENSE.md
takeover.py-1.0.0.dist-info/METADATA
takeover.py-1.0.0.dist-info/WHEEL
takeover.py-1.0.0.dist-info/entry_points.txt
takeover.py-1.0.0.dist-info/top_level.txt
takeover.py-1.0.0.dist-info/RECORD
