Metadata-Version: 2.1
Name: takeover.py
Version: 1.0.0
Summary: This small script tries to detect subdomain takeovers from a list of domains. Fingerprints are taken from https://github.com/EdOverflow/can-i-take-over-xyz.
Home-page: http://github.com/0xcrypto/takeover
Author: Vikrant Singh Chauhan
Author-email: vi@hackberry.xyz
License: MIT
Keywords: subdomain takeover
Platform: UNKNOWN
Classifier: Development Status :: 3 - Alpha
Classifier: Topic :: Security
Classifier: License :: OSI Approved :: MIT License
Requires-Dist: requests
Requires-Dist: dnspython
Requires-Dist: click
Requires-Dist: selenium
